{
  "config": {
    "token": "2bb98bd4ac8ac496c032536939206a06b7509ca7bafbed7e6724de7ba7ca13fd5013701466430e1fa2d61"
  },
  "locale": {
    "current_collection_button": "Актуальная коллекция",
    "current_collection_button_color": "primary",
    "discounts_button": "Скидки",
    "discounts_button_color": "secondary",
    "need_help_button": "Помощь менеджера",
    "need_help_button_color": "negative",
    "about_button": "О нас",
    "about_button_color": "positive",
    "back_button": "Назад",
    "back_button_color": "positive",

    "manager_start_message": "Кожаный мешок уже в пути!",
    "manager_end_message": "Тикет закрыт!",
    "message_to_close_ticket": "/close",

    "main_menu_text": "Самый сложный выбор...",
    "current_collection_text": "Самая актуальная коллекция:",
    "discounts_text": "Самые актуальные скидки",
    "about_text": "О нас текст написан очень круто\n\nЯ люблю пить воду\nAezakmi пж",
    "about_image": "photo510101451_456239018,photo510101451_456239018,photo510101451_456239018,photo510101451_456239018",

    "current_collection_legacy_text": {
      "photos": "photo510101451_456239018,photo510101451_456239018",
      "text": "Текст поддерживает перенос \nстроки, эмоджи 😢 и другие прикольные штуки"
    },
    "current_collection_carousel": {
      "photos": ["-109837093_457242811", "-109837093_457242811", "-109837093_457242811"],
      "text": ["Кол-во строчек", "должно соответствовать", "кол-ву картинок"],
      "description": ["Кол-во строчек", "должно соответствовать", "кол-ву картинок"],
      "button_text": ["Описание", "Такое же кол-во", "Или не прочитается"],
      "button_links": ["https://google.com", "https://youtube.com", "https://www.gtavicecity.ru/gta-san-andreas/gta-san-andreas-cheats-pc.html"]
    },

    "discounts_legacy_text": {
      "photos": "photo510101451_456239018,photo510101451_456239018",
      "text": "Текст поддерживает перенос \nстроки, эмоджи 😢 и другие прикольные штуки"
    },
    "discounts_carousel": {
      "photos": ["-109837093_457242811", "-109837093_457242811", "-109837093_457242811"],
      "text": ["Кол-во строчек", "должно соответствовать", "кол-ву картинок"],
      "description": ["Кол-во строчек", "должно соответствовать", "кол-ву картинок"],
      "button_text": ["Описание", "Такое же кол-во", "Или не прочитается"],
      "button_links": ["https://google.com", "https://youtube.com", "https://www.gtavicecity.ru/gta-san-andreas/gta-san-andreas-cheats-pc.html"]
    }
  }
}